edge_ml-0.4.0.dist-info/licenses/LICENSE
edgeml/Dataset.py
edgeml/Labeling.py
edgeml/TimeSeries.py
edgeml/__init__.py
edgeml/consts.py
edgeml/edgeml.py
edge_ml-0.4.0.dist-info/METADATA
edge_ml-0.4.0.dist-info/WHEEL
edge_ml-0.4.0.dist-info/top_level.txt
edge_ml-0.4.0.dist-info/RECORD
