Metadata-Version: 2.4
Name: edge-ml
Version: 0.4.0
Summary: ```python
Author-email: KIT/TECO <info@edge-ml.org>
Project-URL: Home, https://github.com/edge-ml/python
Classifier: License :: OSI Approved :: MIT License
License-File: LICENSE
Dynamic: license-file
